twarchive/__init__.py
twarchive/cli.py
twarchive/hugo.py
twarchive/testutil.py
twarchive/twitterapi.py
twarchive/twitterarchive.py
twarchive/util.py
twarchive/version.py
twarchive/inflatedtweet/__init__.py
twarchive/inflatedtweet/body.py
twarchive/inflatedtweet/from_tweepy.py
twarchive/inflatedtweet/from_twitter_archive.py
twarchive/inflatedtweet/inflatedtweet.py
twarchive/inflatedtweet/inflmedia.py
twarchive-0.5.4.dist-info/METADATA
twarchive-0.5.4.dist-info/WHEEL
twarchive-0.5.4.dist-info/entry_points.txt
twarchive-0.5.4.dist-info/top_level.txt
twarchive-0.5.4.dist-info/RECORD
