Metadata-Version: 2.1
Name: twarchive
Version: 0.5.4
Summary: Download tweets for use with the twarchive Hugo theme
Home-page: https://github.com/mrled/twarchive/
Author: Micah R Ledbetter
Author-email: me@micahrl.com
Requires-Python: >=3.9
Requires-Dist: tweepy
